ngm/__init__.py
ngm/__main__.py
ngm/services/3040.py
ngm/services/585gold.py
ngm/services/admiralxxx.py
ngm/services/aitu.py
ngm/services/alfalife.py
ngm/services/alpari.py
ngm/services/apteka.py
ngm/services/atprime.py
ngm/services/av.py
ngm/services/banki.py
ngm/services/benzuber.py
ngm/services/betmaster.py
ngm/services/btfair.py
ngm/services/carsmile.py
ngm/services/citilink.py
ngm/services/city24.py
ngm/services/creditter.py
ngm/services/delimobil.py
ngm/services/dostavista.py
ngm/services/easypay.py
ngm/services/etm.py
ngm/services/finam.py
ngm/services/findclone.py
ngm/services/fixprice.py
ngm/services/flipkart.py
ngm/services/foodband.py
ngm/services/gurutaxi.py
ngm/services/hatimaki.py
ngm/services/helsi.py
ngm/services/icq.py
ngm/services/indriver.py
ngm/services/ingos.py
ngm/services/invitro.py
ngm/services/iqos.py
ngm/services/ivi.py
ngm/services/karusel.py
ngm/services/kfc.py
ngm/services/kinoland.py
ngm/services/koronopay.py
ngm/services/lenta.py
ngm/services/limetaxi.py
ngm/services/mailrucloud.py
ngm/services/makimaki.py
ngm/services/menu.py
ngm/services/menzacafe.py
ngm/services/mobileplanet.py
ngm/services/monobank.py
ngm/services/mospizza.py
ngm/services/mousam.py
ngm/services/moyo.py
ngm/services/mtstv.py
ngm/services/multiplex.py
ngm/services/mvideo.py
ngm/services/mygames.py
ngm/services/niyama.py
ngm/services/nl.py
ngm/services/ok.py
ngm/services/okeansushi.py
ngm/services/ollis.py
ngm/services/onlineua.py
ngm/services/ontaxi.py
ngm/services/ozon.py
ngm/services/panda99.py
ngm/services/pizzasushiwok.py
ngm/services/planetakino.py
ngm/services/plink.py
ngm/services/qlean.py
ngm/services/redmondeda.py
ngm/services/rutaxi.py
ngm/services/rutube.py
ngm/services/sberfood.py
ngm/services/service.py
ngm/services/shopandshow.py
ngm/services/sipnet.py
ngm/services/smartspace.py
ngm/services/sportmaster.py
ngm/services/sunlight.py
ngm/services/sushi33.py
ngm/services/sushimaster.py
ngm/services/sushiprofi.py
ngm/services/tanuki.py
ngm-3.5.2.dist-info/LICENSE
ngm-3.5.2.dist-info/METADATA
ngm-3.5.2.dist-info/WHEEL
ngm-3.5.2.dist-info/entry_points.txt
ngm-3.5.2.dist-info/top_level.txt
ngm-3.5.2.dist-info/RECORD
